spindle_detector/__init__.py
spindle_detector/core.py
spindle_detector/lfp_likelihood.py
spindle_detector/simulate_LFP.py
spindle_detector-0.1.0.dev0.dist-info/LICENSE
spindle_detector-0.1.0.dev0.dist-info/METADATA
spindle_detector-0.1.0.dev0.dist-info/WHEEL
spindle_detector-0.1.0.dev0.dist-info/top_level.txt
spindle_detector-0.1.0.dev0.dist-info/RECORD
