Metadata-Version: 2.1
Name: spindle-detector
Version: 0.1.0.dev0
Summary: Identify spindle events
Home-page: https://github.com/Eden-Kramer-Lab/spindle_detector
Author: UNKNOWN
Author-email: UNKNOWN
License: MIT
Platform: UNKNOWN
Requires-Dist: numpy (>=1.14)
Requires-Dist: matplotlib
Requires-Dist: pandas
Requires-Dist: scipy
Requires-Dist: scikit-learn
Requires-Dist: spectral-connectivity
Requires-Dist: hmmlearn
